sebi_parser/DocumentExtractor.py
sebi_parser/__init__.py
sebi_parser/cli.py
sebi_parser/sebi.py
sebi_main_parser-1.0.0.dist-info/METADATA
sebi_main_parser-1.0.0.dist-info/WHEEL
sebi_main_parser-1.0.0.dist-info/entry_points.txt
sebi_main_parser-1.0.0.dist-info/top_level.txt
sebi_main_parser-1.0.0.dist-info/RECORD
