Metadata-Version: 2.4
Name: sebi-main-parser
Version: 1.0.0
Summary: SEBI PDF parser and summarizer
Author-email: Devam Kumar <devamkumar758@gmail.com>
Requires-Python: >=3.8
Requires-Dist: spacy>=3.7.0
Requires-Dist: transformers
Requires-Dist: torch
Requires-Dist: pymupdf
Requires-Dist: requests
Requires-Dist: beautifulsoup4
